<?xml version="1.0" encoding="UTF-8"?><!--Transformation version 1.3--><legislativeDoc xmlns:xsi="http://www.w3.org/2001/XMLSchema-instance" xsi:noNamespaceSchemaLocation="http://www.lexisnexis.com/xmlschemas/content/public/legislativedoc/1/" schemaVersion="1.0"><legislativeDocHead><citations><citeForThisResource citeDefinition="#7159#349#000038#     2#         4517#">Va. Code Ann. § 38.2-4517</citeForThisResource></citations><legislativeBodyInfo><jurisdiction><jurisSystem normalizedLongName="Virginia" normalizedShortName="VA"/></jurisdiction></legislativeBodyInfo></legislativeDocHead><legislativeDocBody><statute><level levelType="section"><anchor id="_38.2-4517"/><heading><desig>§ 38.2-4517.</desig><title>Licensing of nonstock corporation</title></heading><level levelType="paragraph"><anchor id="_a"/><heading><desig>A.</desig></heading><bodyText><p> No person shall operate a dental or optometric services plan in this Commonwealth without a license issued by the Commission. Each nonstock corporation shall apply for a license and furnish any relevant information the Commission requires. Each license shall expire at midnight on the following June 30. Application for a license shall be accompanied by a nonrefundable application fee of $ 500.</p></bodyText></level><level levelType="paragraph"><anchor id="_b"/><heading><desig>B.</desig></heading><bodyText><p> The Commission shall not issue to or renew a license of a nonstock corporation unless it is satisfied that the financial condition, the method of operation, and the manner of doing business of the nonstock corporation enable it to meet its contractual obligations to all subscribers and that the nonstock corporation has otherwise complied with all the requirements of law.</p></bodyText></level><history><historyGroup groupType="history-citation"><historyItem><bodyText><p>1980, c. 682, § 38.1-906; 1986, c. 562; 1987, cc. 565, 655; <citation normalizedCite="1994 VA CH 503"><content><span normalizedCite="1994 Va. Ch. 503">1994, c. 503<locator><locatorKey><keyName name="citeReference"/><keyValue value="#1834#131#1994#000503#"/></locatorKey></locator></span></content></citation>.</p></bodyText></historyItem></historyGroup></history></level></statute></legislativeDocBody><metadata><dc:metadata xmlns:dc="http://purl.org/dc/elements/1.1/"><dc:identifier identifierScheme="PGUID">urn:contentItem:5K0Y-PT60-004G-K020-00000-00</dc:identifier><dc:source sourceScheme="productContentSetIdentifier">10816</dc:source><dc:date dateType="last-updated">2016-06-15</dc:date></dc:metadata><publicationInfo><publicationName>CODE OF VIRGINIA </publicationName><copyright>Copyright © 2016  by Matthew Bender &amp; Company, Inc. a member of the LexisNexis Group. All rights reserved</copyright></publicationInfo><hierarchy><hierarchyLevel levelType="title"><heading><desig>TITLE 38.2.</desig><title>INSURANCE</title></heading><hierarchyLevel levelType="chapter"><heading><desig>CHAPTER 45.</desig><title>DENTAL OR OPTOMETRIC SERVICES PLANS</title></heading></hierarchyLevel></hierarchyLevel></hierarchy><classification classificationScheme="legal"><classificationItem><className>Healthcare Law</className><classCode>Z3VpZD11cm46dG9waWM6NkUxMkVDQjJDOEY5NDVDQ0E5NTFEMTlDMjIwNzVERjc7cGFyZW50Z3VpZD0</classCode><classificationItem><className>Personnel Licensing</className><classCode>Z3VpZD11cm46dG9waWM6M0VCMTAwM0MwNDA1NEI4OThDNUVEMEIwRTJDQjU2QTM7cGFyZW50Z3VpZD11cm46dG9waWM6QTJGRDdFQzgwODczNDI0NDgwMzEyM0JBOEQ2MUVDNjg</classCode></classificationItem></classificationItem></classification><classificationGroup classificationScheme="indexing-terms"><classification classificationScheme="legal"><classificationItem><className>Business &amp; Corporate Compliance</className><classCode>Z3VpZD11cm46dG9waWM6MUFEMUQ2QTA1OUZCNEE5RjkzNTA2RERFMUNEOTk1RTI7cGFyZW50Z3VpZD0</classCode><classificationItem score="90"><className>Insurance</className><classCode>Z3VpZD11cm46dG9waWM6MDM4MzQ2QUYzMTY0NDQzQTkxRDQwRUUzRUM5RDg0OEM7cGFyZW50Z3VpZD11cm46dG9waWM6MUFEMUQ2QTA1OUZCNEE5RjkzNTA2RERFMUNEOTk1RTI</classCode></classificationItem></classificationItem></classification></classificationGroup></metadata></legislativeDoc>