<?xml version="1.0" encoding="UTF-8"?><!--Transformation version 1.3--><legislativeDoc xmlns:xsi="http://www.w3.org/2001/XMLSchema-instance" xsi:noNamespaceSchemaLocation="http://www.lexisnexis.com/xmlschemas/content/public/legislativedoc/1/" schemaVersion="1.0"><legislativeDocHead><citations><citeForThisResource citeDefinition="#7159#349#000028#     2#          510#">Va. Code Ann. § 28.2-510</citeForThisResource></citations><legislativeBodyInfo><jurisdiction><jurisSystem normalizedLongName="Virginia" normalizedShortName="VA"/></jurisdiction></legislativeBodyInfo></legislativeDocHead><legislativeDocBody><statute><level levelType="section"><anchor id="_28.2-510"/><heading><desig>§ 28.2-510.</desig><title>Buying, selling, or possessing unculled oysters; penalty</title></heading><bodyText><p>It is unlawful for any person to buy, sell, or possess oysters under the prescribed size and over the shell allowance taken from the public rocks, beds, and shoals.  If upon trial for this offense the accused person asserts the claim or defense that the unculled oysters were taken from private planting grounds, the burden of proving such a defense or fact shall be upon the accused.</p><p>A violation of any provision of this section is a Class 3 misdemeanor.</p></bodyText><history><historyGroup groupType="history-citation"><historyItem><bodyText><p>Code 1950, §§ 28-142, 28-146; 1960, c. 517; 1962, c. 406, §§ 28.1-125, 28.1-127; 1985, c. 125; <citation normalizedCite="1992 VA CH 836"><content><span normalizedCite="1992 Va. Ch. 836">1992, c. 836<locator><locatorKey><keyName name="citeReference"/><keyValue value="#1834#131#1992#000836#"/></locatorKey></locator></span></content></citation>.</p></bodyText></historyItem></historyGroup></history></level></statute></legislativeDocBody><metadata><dc:metadata xmlns:dc="http://purl.org/dc/elements/1.1/"><dc:identifier identifierScheme="PGUID">urn:contentItem:5K0Y-PV40-004G-K3N8-00000-00</dc:identifier><dc:source sourceScheme="productContentSetIdentifier">10816</dc:source><dc:date dateType="last-updated">2016-06-15</dc:date></dc:metadata><publicationInfo><publicationName>CODE OF VIRGINIA </publicationName><copyright>Copyright © 2016  by Matthew Bender &amp; Company, Inc. a member of the LexisNexis Group. All rights reserved</copyright></publicationInfo><hierarchy><hierarchyLevel levelType="title"><heading><desig>TITLE 28.2.</desig><title>FISHERIES AND HABITAT OF THE TIDAL WATERS</title></heading><hierarchyLevel levelType="subtitle"><heading><desig>SUBTITLE II.</desig><title>TIDAL FISHERIES</title></heading><hierarchyLevel levelType="chapter"><heading><desig>CHAPTER 5.</desig><title>OYSTERS AND CLAMS</title></heading><hierarchyLevel levelType="article"><heading><desig>ARTICLE 2.</desig><title>FISHING FOR OYSTERS AND CLAMS; DEVICE RESTRICTIONS</title></heading></hierarchyLevel></hierarchyLevel></hierarchyLevel></hierarchyLevel></hierarchy><classification classificationScheme="legal"><classificationItem><className>Criminal Law &amp; Procedure</className><classCode>Z3VpZD11cm46dG9waWM6NEU0RkE1OUQwNUQwNDgxODhEODZCMjkzOTg3NThBNzk7cGFyZW50Z3VpZD0</classCode><classificationItem><className>Burdens of Proof</className><classCode>Z3VpZD11cm46dG9waWM6QzhEMUQ4QkQzNjQzNDU4MEI2NUYzRUVDMzVFNjIyMDI7cGFyZW50Z3VpZD11cm46dG9waWM6RTQ4OTRGNzEyNzlDNEE2N0E1NDExQTVERDlCODY2ODA</classCode></classificationItem><classificationItem><className>General Overview</className><classCode>Z3VpZD11cm46dG9waWM6NUY3NTAwNEIwRUNCNDRCMkIyQjNCNUE3NjREODIzRkQ7cGFyZW50Z3VpZD11cm46dG9waWM6RTQ4OTRGNzEyNzlDNEE2N0E1NDExQTVERDlCODY2ODA</classCode></classificationItem></classificationItem></classification></metadata></legislativeDoc>