<?xml version="1.0" encoding="UTF-8"?><!--Transformation version 1.3--><legislativeDoc xmlns:xsi="http://www.w3.org/2001/XMLSchema-instance" xsi:noNamespaceSchemaLocation="http://www.lexisnexis.com/xmlschemas/content/public/legislativedoc/1/" schemaVersion="1.0"><legislativeDocHead><citations><citeForThisResource citeDefinition="#7159#123#000050#     73.80#">Va. Code Ann. § 50-73.80</citeForThisResource></citations><legislativeBodyInfo><jurisdiction><jurisSystem normalizedLongName="Virginia" normalizedShortName="VA"/></jurisdiction></legislativeBodyInfo></legislativeDocHead><legislativeDocBody><statute><level levelType="section"><anchor id="_50-73.80"/><heading><desig>§ 50-73.80.</desig><title>Knowledge and notice</title></heading><level levelType="paragraph"><anchor id="_a"/><heading><desig>A.</desig></heading><bodyText><p> A person knows a fact if the person has actual knowledge of it.</p></bodyText></level><level levelType="paragraph"><anchor id="_b"/><heading><desig>B.</desig></heading><bodyText><p> A person has notice of a fact if the person:</p></bodyText><level levelType="paragraph"><anchor id="_b_1"/><heading><desig>1.</desig></heading><bodyText><p> Knows of it;</p></bodyText></level><level levelType="paragraph"><anchor id="_b_2"/><heading><desig>2.</desig></heading><bodyText><p> Has received a notification of it; or</p></bodyText></level><level levelType="paragraph"><anchor id="_b_3"/><heading><desig>3.</desig></heading><bodyText><p> Has reason to know it exists from all of the facts known to the person at the time in question.</p></bodyText></level></level><level levelType="paragraph"><anchor id="_c"/><heading><desig>C.</desig></heading><bodyText><p> A person notifies or gives a notification to another by taking steps reasonably calculated to inform the other person in ordinary course, whether or not the other person learns of it.</p></bodyText></level><level levelType="paragraph"><anchor id="_d"/><heading><desig>D.</desig></heading><bodyText><p> A person receives a notification when the notification:</p></bodyText><level levelType="paragraph"><anchor id="_d_1"/><heading><desig>1.</desig></heading><bodyText><p> Comes to the person's attention; or</p></bodyText></level><level levelType="paragraph"><anchor id="_d_2"/><heading><desig>2.</desig></heading><bodyText><p> Is duly delivered at the person's place of business or at any other place held out by the person as a place for receiving communications.</p></bodyText></level></level><level levelType="paragraph"><anchor id="_e"/><heading><desig>E.</desig></heading><bodyText><p> Except as otherwise provided in subsection F, a person other than an individual knows, has notice, or receives a notification of a fact for purposes of a particular transaction when the individual conducting the transaction knows, has notice, or receives a notification of the fact, or in any event when the fact would have been brought to the individual's attention if the person had exercised reasonable diligence. The person exercises reasonable diligence if it maintains reasonable routines for communicating significant information to the individual conducting the transaction and there is reasonable compliance with the routines. Reasonable diligence does not require an individual acting for the person to communicate information unless the communication is part of the individual's regular duties or the individual has reason to know of the transaction and that the transaction would be materially affected by the information.</p></bodyText></level><level levelType="paragraph"><anchor id="_f"/><heading><desig>F.</desig></heading><bodyText><p> A partner's knowledge, notice, or receipt of a notification of a fact relating to the partnership is effective immediately as knowledge by, notice to, or receipt of a notification by the partnership, except in the case of a fraud on the partnership committed by or with the consent of that partner.</p></bodyText></level><history><historyGroup groupType="history-citation"><historyItem><bodyText><p><citation normalizedCite="1996 VA CH 292"><content><span normalizedCite="1996 Va. Ch. 292">1996, c. 292<locator><locatorKey><keyName name="citeReference"/><keyValue value="#1834#131#1996#000292#"/></locatorKey></locator></span></content></citation>.</p></bodyText></historyItem></historyGroup></history></level></statute></legislativeDocBody><metadata><dc:metadata xmlns:dc="http://purl.org/dc/elements/1.1/"><dc:identifier identifierScheme="PGUID">urn:contentItem:5K0Y-PV10-004G-K1M5-00000-00</dc:identifier><dc:source sourceScheme="productContentSetIdentifier">10816</dc:source><dc:date dateType="last-updated">2016-06-15</dc:date></dc:metadata><publicationInfo><publicationName>CODE OF VIRGINIA </publicationName><copyright>Copyright © 2016  by Matthew Bender &amp; Company, Inc. a member of the LexisNexis Group. All rights reserved</copyright></publicationInfo><hierarchy><hierarchyLevel levelType="title"><heading><desig>TITLE 50.</desig><title>PARTNERSHIPS</title></heading><hierarchyLevel levelType="chapter"><heading><desig>CHAPTER 2.2.</desig><title>VIRGINIA UNIFORM PARTNERSHIP ACT</title></heading><hierarchyLevel levelType="article"><heading><desig>ARTICLE 1.</desig><title>GENERAL PROVISIONS</title></heading></hierarchyLevel></hierarchyLevel></hierarchyLevel></hierarchy><classificationGroup classificationScheme="indexing-terms"><classification classificationScheme="legal"><classificationItem><className>Business &amp; Corporate Compliance</className><classCode>Z3VpZD11cm46dG9waWM6MUFEMUQ2QTA1OUZCNEE5RjkzNTA2RERFMUNEOTk1RTI7cGFyZW50Z3VpZD0</classCode><classificationItem score="90"><className>Businesses &amp; Corporations</className><classCode>Z3VpZD11cm46dG9waWM6QjA4OEVGODBENzY4NDcxM0IyQzA1OTEwQzVDODRBOUE7cGFyZW50Z3VpZD11cm46dG9waWM6MUFEMUQ2QTA1OUZCNEE5RjkzNTA2RERFMUNEOTk1RTI</classCode></classificationItem></classificationItem></classification></classificationGroup></metadata></legislativeDoc>