<?xml version="1.0" encoding="UTF-8"?><!--Transformation version 1.3--><legislativeDoc xmlns:xsi="http://www.w3.org/2001/XMLSchema-instance" xsi:noNamespaceSchemaLocation="http://www.lexisnexis.com/xmlschemas/content/public/legislativedoc/1/" schemaVersion="1.0"><legislativeDocHead><citations><citeForThisResource citeDefinition="#7159#349#000037#     2#        817.1#">Va. Code Ann. § 37.2-817.1</citeForThisResource></citations><legislativeBodyInfo><jurisdiction><jurisSystem normalizedLongName="Virginia" normalizedShortName="VA"/></jurisdiction></legislativeBodyInfo></legislativeDocHead><legislativeDocBody><statute><level levelType="section"><anchor id="_37.2-817.1"/><heading><desig>§ 37.2-817.1.</desig><title>Monitoring mandatory outpatient treatment; petition for hearing</title></heading><level levelType="paragraph"><anchor id="_a"/><heading><desig>A.</desig></heading><bodyText><p> The community services board where the person resides shall monitor the person's compliance with the mandatory outpatient treatment plan or discharge plan ordered by the court pursuant to <citation type="statute" normalizedCite="VACODE 37.2-817"><content><span normalizedCite="Va. Code Ann. § 37.2-817">§ 37.2-817<locator><locatorKey><keyName name="citeReference"/><keyValue value="#7159#349#000037#     2#          817#"/></locatorKey></locator></span></content></citation>. Monitoring compliance shall include (i) contacting the service providers to determine if the person is complying with the mandatory outpatient treatment order or order authorizing discharge to mandatory outpatient treatment following inpatient treatment and (ii) notifying the court of the person's material noncompliance with the mandatory outpatient treatment order or order authorizing discharge to mandatory outpatient treatment following inpatient treatment. Providers of services identified in the plan shall report any material noncompliance to the community services board.</p></bodyText></level><level levelType="paragraph"><anchor id="_b"/><heading><desig>B.</desig></heading><bodyText><p> If the community services board determines that the person materially failed to comply with the order, it shall petition the court for a review of the mandatory outpatient treatment order or order authorizing discharge to mandatory outpatient treatment following inpatient treatment as provided in <citation type="statute" normalizedCite="VACODE 37.2-817.2"><content><span normalizedCite="Va. Code Ann. § 37.2-817.2">§ 37.2-817.2.<locator><locatorKey><keyName name="citeReference"/><keyValue value="#7159#349#000037#     2#        817.2#"/></locatorKey></locator></span></content></citation> The community services board shall petition the court for a review of the mandatory outpatient treatment order or order authorizing discharge to mandatory outpatient treatment following inpatient treatment within three days of making that determination, or within 24 hours if the person is being detained under a temporary detention order, and shall recommend an appropriate disposition. Copies of the petition shall be sent to the person and the person's attorney.</p></bodyText></level><level levelType="paragraph"><anchor id="_c"/><heading><desig>C.</desig></heading><bodyText><p> If the community services board determines that the person is not materially complying with the mandatory outpatient treatment order or order authorizing discharge to mandatory outpatient treatment following inpatient treatment or for any other reason, and there is a substantial likelihood that, as a result of the person's mental illness that the person will, in the near future, (i) cause serious physical harm to himself or others as evidenced by recent behavior causing, attempting or threatening harm and other relevant information, if any, or (ii) suffer serious harm due to his lack of capacity to protect himself from harm or to provide for his basic human needs, it shall immediately request that the magistrate issue an emergency custody order pursuant to <citation type="statute" normalizedCite="VACODE 37.2-808"><content><span normalizedCite="Va. Code Ann. § 37.2-808">§ 37.2-808<locator><locatorKey><keyName name="citeReference"/><keyValue value="#7159#349#000037#     2#          808#"/></locatorKey></locator></span></content></citation> or a temporary detention order pursuant to <citation type="statute" normalizedCite="VACODE 37.2-809"><content><span normalizedCite="Va. Code Ann. § 37.2-809">§ 37.2-809<locator><locatorKey><keyName name="citeReference"/><keyValue value="#7159#349#000037#     2#          809#"/></locatorKey></locator></span></content></citation>.</p></bodyText></level><history><historyGroup groupType="history-citation"><historyItem><bodyText><p><citation normalizedCite="2008 VA CH 850"><content><span normalizedCite="2008 Va. Ch. 850">2008, cc. 850<locator><locatorKey><keyName name="citeReference"/><keyValue value="#1834#131#2008#000850#"/></locatorKey></locator></span></content></citation>, <citation normalizedCite="2008 VA CH 870"><content><span normalizedCite="2008 Va. Ch. 870">870<locator><locatorKey><keyName name="citeReference"/><keyValue value="#1834#131#2008#000870#"/></locatorKey></locator></span></content></citation>; <citation normalizedCite="2010 VA CH 330"><content><span normalizedCite="2010 Va. Ch. 330">2010, cc. 330<locator><locatorKey><keyName name="citeReference"/><keyValue value="#1834#131#2010#000330#"/></locatorKey></locator></span></content></citation>, <citation normalizedCite="2010 VA CH 461"><content><span normalizedCite="2010 Va. Ch. 461">461<locator><locatorKey><keyName name="citeReference"/><keyValue value="#1834#131#2010#000461#"/></locatorKey></locator></span></content></citation>.</p></bodyText></historyItem></historyGroup></history></level></statute></legislativeDocBody><metadata><dc:metadata xmlns:dc="http://purl.org/dc/elements/1.1/"><dc:identifier identifierScheme="PGUID">urn:contentItem:5K0Y-PVJ0-004G-K17K-00000-00</dc:identifier><dc:source sourceScheme="productContentSetIdentifier">10816</dc:source><dc:date dateType="last-updated">2016-06-15</dc:date></dc:metadata><publicationInfo><publicationName>CODE OF VIRGINIA </publicationName><copyright>Copyright © 2016  by Matthew Bender &amp; Company, Inc. a member of the LexisNexis Group. All rights reserved</copyright></publicationInfo><hierarchy><hierarchyLevel levelType="title"><heading><desig>TITLE 37.2.</desig><title>BEHAVIORAL HEALTH AND DEVELOPMENTAL SERVICES</title></heading><hierarchyLevel levelType="subtitle"><heading><desig>SUBTITLE 3.</desig><title>ADMISSIONS AND DISPOSITIONS</title></heading><hierarchyLevel levelType="chapter"><heading><desig>CHAPTER 8.</desig><title>EMERGENCY CUSTODY AND VOLUNTARY AND INVOLUNTARY CIVIL ADMISSIONS</title></heading><hierarchyLevel levelType="article"><heading><desig>ARTICLE 5.</desig><title>INVOLUNTARY ADMISSIONS</title></heading></hierarchyLevel></hierarchyLevel></hierarchyLevel></hierarchyLevel></hierarchy><classification classificationScheme="legal"><classificationItem><className>Criminal Law &amp; Procedure</className><classCode>Z3VpZD11cm46dG9waWM6NEU0RkE1OUQwNUQwNDgxODhEODZCMjkzOTg3NThBNzk7cGFyZW50Z3VpZD0</classCode><classificationItem><className>Detention</className><classCode>Z3VpZD11cm46dG9waWM6NjhEMjRDMkUwQTJDNDNEQTk1MTZGOTQ1NDRGN0FGNUM7cGFyZW50Z3VpZD11cm46dG9waWM6QTc2N0NFQzYyRUE3NDZBMTk3REExRTgyMUQ4OEY4MjU</classCode></classificationItem></classificationItem><classificationItem><className>Public Health &amp; Welfare Law</className><classCode>Z3VpZD11cm46dG9waWM6NDYwRTY1MDg3MTk5NDUyNkFFRDI1RjJBRERGQ0UxNzI7cGFyZW50Z3VpZD0</classCode><classificationItem><className>Discharge &amp; Release of Adults</className><classCode>Z3VpZD11cm46dG9waWM6QkYyOEQ5NDlGQUNFNDdFMjlBNDA4MkJFMThERkQ3NjM7cGFyZW50Z3VpZD11cm46dG9waWM6QkQzMjQzQzhBQUQ2NDRBQTg4MjYwMzQ0QTI0N0E3RTQ</classCode></classificationItem></classificationItem></classification></metadata></legislativeDoc>