<?xml version="1.0" encoding="UTF-8"?><!--Transformation version 1.3--><legislativeDoc xmlns:xsi="http://www.w3.org/2001/XMLSchema-instance" xsi:noNamespaceSchemaLocation="http://www.lexisnexis.com/xmlschemas/content/public/legislativedoc/1/" schemaVersion="1.0"><legislativeDocHead><citations><citeForThisResource citeDefinition="#7159#349#000015#     2#         2404#">Va. Code Ann. § 15.2-2404</citeForThisResource></citations><legislativeBodyInfo><jurisdiction><jurisSystem normalizedLongName="Virginia" normalizedShortName="VA"/></jurisdiction></legislativeBodyInfo></legislativeDocHead><legislativeDocBody><statute><level levelType="section"><anchor id="_15.2-2404"/><heading><desig>§ 15.2-2404.</desig><title>Authority to impose taxes or assessments for local improvements; purposes</title></heading><level levelType="paragraph"><anchor id="_a"/><heading><desig>A.</desig></heading><bodyText><p> A locality may impose taxes or assessments upon the owners of abutting property for constructing, improving, replacing or enlarging the sidewalks upon existing streets, for improving and paving existing alleys, and for the construction or the use of sanitary or storm water management facilities, retaining walls, curbs and gutters. Such taxes or assessments may include the legal, financial or other directly attributable costs incurred by the locality in creating a district, if a district is created, and financing the payment of the improvements. The taxes or assessments shall not be in excess of the peculiar benefits resulting from the improvements to such abutting property owners. No tax or assessment for retaining walls shall be imposed upon any property owner who does not agree to such tax or assessment.</p></bodyText></level><level levelType="paragraph"><anchor id="_b"/><heading><desig>B.</desig></heading><bodyText><p> In addition to the foregoing, a locality may impose taxes or assessments upon the owners of abutting property for the construction, replacement or enlargement of waterlines; for the installation of street lights; for the construction or installation of canopies or other weather protective devices; for the installation of lighting in connection with the foregoing; and for permanent amenities, including, but not limited to, benches or waste receptacles. With regard to installation of street lights, a locality may provide by ordinance that upon a petition of at least 60 percent of the property owners within a subdivision, or such higher percent as provided in the ordinance, the locality may impose taxes or assessments upon all owners within the subdivision who benefit from such improvements. The taxes or assessments shall not be in excess of the peculiar benefits resulting from the improvements to such property owners.</p></bodyText></level><level levelType="paragraph"><anchor id="_c"/><heading><desig>C.</desig></heading><bodyText><p> In the Cities of Chesapeake, Hampton, Hopewell, Newport News, Norfolk, Richmond, and Virginia Beach, the governing body may impose taxes or assessments upon the abutting property owners for the initial improving and paving of an existing street provided not less than 50 percent of such abutting property owners who own not less than 50 percent of the property abutting such street request the improvement or paving. The taxes or assessments permitted by this paragraph shall not be in excess of the peculiar benefits resulting from the improvements to such abutting property owners and in no event shall such amount exceed the sum of $ 10 per front foot of property abutting such street or the sum of $ 1,000 for any one subdivided lot or parcel abutting such street, whichever is the lesser.</p></bodyText></level><level levelType="paragraph"><anchor id="_d"/><heading><desig>D.</desig></heading><bodyText><p> The governing bodies of the Cities of Buena Vista, Hampton, and Waynesboro and the County of Augusta may, by duly adopted ordinance, impose taxes or assessments upon abutting property owners subjected to frequent flooding for special benefits conferred upon that property by the installation or construction of flood control barriers, equipment or other improvements for the prevention of flooding in such area and shall provide for the payment of all or any part of the above projects out of the proceeds of such taxes or assessments, provided that such taxes or assessments shall not be in excess of the peculiar benefits resulting from the improvements to such abutting property owners.</p></bodyText></level><level levelType="paragraph"><anchor id="_e"/><heading><desig>E.</desig></heading><bodyText><p> In the Cities of Hampton, Poquoson and Williamsburg, the governing body may impose taxes or assessments upon the owners of abutting property for the underground relocation of distribution lines for electricity, telephone, cable television and similar utilities. Notwithstanding the provisions of <citation type="statute" normalizedCite="VACODE 15.2-2405"><content><span normalizedCite="Va. Code Ann. § 15.2-2405">§ 15.2-2405<locator><locatorKey><keyName name="citeReference"/><keyValue value="#7159#349#000015#     2#         2405#"/></locatorKey></locator></span></content></citation>, such underground relocation of distribution lines may only be ordered by the governing body and the cost thereof apportioned in pursuance of an agreement between the governing body and the abutting landowners. Notice shall be given to the abutting landowners, notifying them when and where they may appear before the governing body, or some committee thereof, or the administrative board or other similar board of the locality to whom the matter may be referred, to be heard in favor of or against such improvements.</p></bodyText></level><level levelType="paragraph"><anchor id="_f"/><heading><desig>F.</desig></heading><bodyText><p> The governing body of any locality may request an electric utility that proposes to construct an overhead electric transmission line of 150 kilovolts or more, any portion of which would be located in such locality, to enter into an agreement with the locality that provides (i) the locality will impose a tax or assessment on electric utility customers in a special rate district in an amount sufficient to cover the utility's additional costs of constructing that portion of the proposed line to be located in such locality, or any smaller portion thereof as the utility and the locality may agree, as an underground rather than an overhead line; (ii) the tax or assessment will be shown as a separate item on such customers' electric bills and will be collected by the utility on behalf of the locality; (iii) the utility will construct, operate, and maintain the agreed portion of the line underground; (iv) the locality will pay to the utility its full additional costs of constructing that portion of the line underground rather than overhead; and (v) such other terms and conditions as the parties may agree. This provision shall not apply, however, to lines in operation as of March 1, 2005.</p><p>If the locality and the utility enter into such an agreement, the locality shall by ordinance (a) set the boundaries of the special rate district within a reasonable distance of the route of that portion of the line to be placed underground pursuant to the agreement, and (b) fix the amount of such tax or assessment, which shall be based on the assessed value of real property within such district. Thereafter, owners of real property comprising not less than 60 percent of the assessed value of real property within such district may petition the locality to impose such tax or assessment. If such petition is filed, the locality shall submit the agreement to the State Corporation Commission on or before the date by which respondents must prefile testimony and exhibits in any application for approval of the line before the State Corporation Commission, which, after notice and opportunity for hearing, shall approve the agreement if it finds it to be in the public interest. If there exists a practicably feasible overhead alternative for construction of the electric transmission line, the State Corporation Commission shall not approve the agreement unless the governing body of every locality in which the underground segment of the line would be located requests the electric utility to construct the line underground in accordance with this subdivision. If the agreement is approved by the State Corporation Commission, the locality shall impose such tax or assessment on electric utility customers within the district, and the locality and the utility shall carry out the agreement according to its terms and conditions.</p></bodyText></level><level levelType="paragraph"><anchor id="_g"/><heading><desig>G.</desig></heading><bodyText><p> In the County of Loudoun, the governing body may impose taxes or assessments upon the abutting property owners of Crooked Bridge Lane, located in the Blue Ridge District, for the improvement of the bridge located on Crooked Bridge Lane, including construction, repair and maintenance, provided not less than 50 percent of such abutting property owners who own not less than 50 percent of the property abutting such street request the improvement. The taxes or assessments permitted by this paragraph shall not be in excess of the peculiar benefits resulting from the improvements to such abutting property owners.</p></bodyText></level><history><historyGroup groupType="history-citation"><historyItem><bodyText><p>Code 1950, § 15-669; 1962, c. 623, § 15.1-239; 1966, c. 127; 1971, Ex. Sess., c. 126; 1972, cc. 704, 767; 1976, cc. 512, 617; 1977, c. 225; 1981, c. 581; 1985, c. 59; <citation normalizedCite="1989 VA CH 24"><content><span normalizedCite="1989 Va. Ch. 24">1989, cc. 24<locator><locatorKey><keyName name="citeReference"/><keyValue value="#1834#131#1989#000024#"/></locatorKey></locator></span></content></citation>, <citation normalizedCite="1989 VA CH 564"><content><span normalizedCite="1989 Va. Ch. 564">564<locator><locatorKey><keyName name="citeReference"/><keyValue value="#1834#131#1989#000564#"/></locatorKey></locator></span></content></citation>; <citation normalizedCite="1991 VA CH 422"><content><span normalizedCite="1991 Va. Ch. 422">1991, c. 422<locator><locatorKey><keyName name="citeReference"/><keyValue value="#1834#131#1991#000422#"/></locatorKey></locator></span></content></citation>; <citation normalizedCite="1997 VA CH 587"><content><span normalizedCite="1997 Va. Ch. 587">1997, c. 587<locator><locatorKey><keyName name="citeReference"/><keyValue value="#1834#131#1997#000587#"/></locatorKey></locator></span></content></citation>; <citation normalizedCite="1998 VA CH 324"><content><span normalizedCite="1998 Va. Ch. 324">1998, cc. 324<locator><locatorKey><keyName name="citeReference"/><keyValue value="#1834#131#1998#000324#"/></locatorKey></locator></span></content></citation>, <citation normalizedCite="1998 VA CH 864"><content><span normalizedCite="1998 Va. Ch. 864">864<locator><locatorKey><keyName name="citeReference"/><keyValue value="#1834#131#1998#000864#"/></locatorKey></locator></span></content></citation>; <citation normalizedCite="1999 VA CH 386"><content><span normalizedCite="1999 Va. Ch. 386">1999, c. 386<locator><locatorKey><keyName name="citeReference"/><keyValue value="#1834#131#1999#000386#"/></locatorKey></locator></span></content></citation>; <citation normalizedCite="2005 VA CH 854"><content><span normalizedCite="2005 Va. Ch. 854">2005, c. 854<locator><locatorKey><keyName name="citeReference"/><keyValue value="#1834#131#2005#000854#"/></locatorKey></locator></span></content></citation>; <citation normalizedCite="2007 VA CH 260"><content><span normalizedCite="2007 Va. Ch. 260">2007, cc. 260<locator><locatorKey><keyName name="citeReference"/><keyValue value="#1834#131#2007#000260#"/></locatorKey></locator></span></content></citation>, <citation normalizedCite="2007 VA CH 813"><content><span normalizedCite="2007 Va. Ch. 813">813<locator><locatorKey><keyName name="citeReference"/><keyValue value="#1834#131#2007#000813#"/></locatorKey></locator></span></content></citation>; <citation normalizedCite="2008 VA CH 355"><content><span normalizedCite="2008 Va. Ch. 355">2008, c. 355<locator><locatorKey><keyName name="citeReference"/><keyValue value="#1834#131#2008#000355#"/></locatorKey></locator></span></content></citation>; <citation normalizedCite="2008 VA CH 8"><content><span normalizedCite="2008 Va. Ch. 8">2008, Sp. Sess. II, c. 8<locator><locatorKey><keyName name="citeReference"/><keyValue value="#1834#131#2008#000008#"/></locatorKey></locator></span></content></citation>; <citation normalizedCite="2009 VA CH 335"><content><span normalizedCite="2009 Va. Ch. 335">2009, c. 335<locator><locatorKey><keyName name="citeReference"/><keyValue value="#1834#131#2009#000335#"/></locatorKey></locator></span></content></citation>; <citation normalizedCite="2010 VA CH 392"><content><span normalizedCite="2010 Va. Ch. 392">2010, c. 392<locator><locatorKey><keyName name="citeReference"/><keyValue value="#1834#131#2010#000392#"/></locatorKey></locator></span></content></citation>; <citation normalizedCite="2012 VA CH 186"><content><span normalizedCite="2012 Va. Ch. 186">2012, cc. 186<locator><locatorKey><keyName name="citeReference"/><keyValue value="#1834#131#2012#000186#"/></locatorKey></locator></span></content></citation>, <citation normalizedCite="2012 VA CH 404"><content><span normalizedCite="2012 Va. Ch. 404">404<locator><locatorKey><keyName name="citeReference"/><keyValue value="#1834#131#2012#000404#"/></locatorKey></locator></span></content></citation>.</p></bodyText></historyItem></historyGroup></history></level></statute></legislativeDocBody><metadata><dc:metadata xmlns:dc="http://purl.org/dc/elements/1.1/"><dc:identifier identifierScheme="PGUID">urn:contentItem:5K0Y-PVN0-004G-K2PG-00000-00</dc:identifier><dc:source sourceScheme="productContentSetIdentifier">10816</dc:source><dc:date dateType="last-updated">2016-06-15</dc:date></dc:metadata><publicationInfo><publicationName>CODE OF VIRGINIA </publicationName><copyright>Copyright © 2016  by Matthew Bender &amp; Company, Inc. a member of the LexisNexis Group. All rights reserved</copyright></publicationInfo><hierarchy><hierarchyLevel levelType="title"><heading><desig>TITLE 15.2.</desig><title>COUNTIES, CITIES AND TOWNS</title></heading><hierarchyLevel levelType="subtitle"><heading><desig>SUBTITLE II.</desig><title>POWERS OF LOCAL GOVERNMENT</title></heading><hierarchyLevel levelType="chapter"><heading><desig>CHAPTER 24.</desig><title>SERVICE DISTRICTS; TAXES AND ASSESSMENTS FOR LOCAL IMPROVEMENTS</title></heading><hierarchyLevel levelType="article"><heading><desig>ARTICLE 2.</desig><title>TAXES OR ASSESSMENTS FOR LOCAL IMPROVEMENTS</title></heading></hierarchyLevel></hierarchyLevel></hierarchyLevel></hierarchyLevel></hierarchy><classification classificationScheme="legal"><classificationItem><className>Business &amp; Corporate Compliance</className><classCode>Z3VpZD11cm46dG9waWM6MUFEMUQ2QTA1OUZCNEE5RjkzNTA2RERFMUNEOTk1RTI7cGFyZW50Z3VpZD0</classCode><classificationItem><className>State &amp; Local Regulation</className><classCode>Z3VpZD11cm46dG9waWM6Qzg5MTM4OTVFMUUzNDQ5MEFBNEY3NTVGMEU0MTkzNzE7cGFyZW50Z3VpZD11cm46dG9waWM6MUJGMzIwOUU1NUY0NDU3MzhFRjhFRkMxQzgxOEI3MEY</classCode></classificationItem><classificationItem><className>Taxation</className><classCode>Z3VpZD11cm46dG9waWM6M0QyRjUyODU2OURFNDJDNEE4NkZCQzRENDE4NEQwODM7cGFyZW50Z3VpZD11cm46dG9waWM6M0E5MjdDNDRFRUIzNEJFNDkyMDk5MThGNTE5M0RFNEU</classCode></classificationItem></classificationItem><classificationItem><className>Communications Law</className><classCode>Z3VpZD11cm46dG9waWM6MEQxMkU0NzE2OEE2NDIxNEE3QzU0NjU2MDRERUNGNDE7cGFyZW50Z3VpZD0</classCode><classificationItem><className>Taxation</className><classCode>Z3VpZD11cm46dG9waWM6M0QyRjUyODU2OURFNDJDNEE4NkZCQzRENDE4NEQwODM7cGFyZW50Z3VpZD11cm46dG9waWM6M0E5MjdDNDRFRUIzNEJFNDkyMDk5MThGNTE5M0RFNEU</classCode></classificationItem></classificationItem><classificationItem><className>Energy &amp; Utilities Law</className><classCode>Z3VpZD11cm46dG9waWM6OUUzODAyRDk1QzVFNEZGMEJDM0RGMDYxOTlEMEEzRDA7cGFyZW50Z3VpZD0</classCode><classificationItem><className>Electricity Transmission</className><classCode>Z3VpZD11cm46dG9waWM6M0FEMjU2NjgxQUJCNDYwOEE2RTU4OUUxOEYxNjQ5MDc7cGFyZW50Z3VpZD11cm46dG9waWM6QjMwQzNCRThDRjkwNDY0QjlFNDJFQzY5QzVCMEE0MTY</classCode></classificationItem><classificationItem><className>General Overview</className><classCode>Z3VpZD11cm46dG9waWM6NjE5MzE1NDYzNDE4NEIzQzhERTAzQjRDRURFRDI5RDQ7cGFyZW50Z3VpZD11cm46dG9waWM6QjNBOTc1MjdCNkU5NENCRDg1OTk1QjQyRjNBNDMwOUU</classCode></classificationItem><classificationItem><className>General Overview</className><classCode>Z3VpZD11cm46dG9waWM6OEFFRkJBRTg3MzUyNDJDMDk5MTA5MDc3NDFDMzlFMjU7cGFyZW50Z3VpZD11cm46dG9waWM6NDgxMjY0MUEwODJFNEQ4RkI3QjhCNUI3ODlFNERFRDY</classCode></classificationItem></classificationItem><classificationItem><className>Governments</className><classCode>Z3VpZD11cm46dG9waWM6MjdEQjE4OUJDMzQxNDNEMEI0RTI1QUFCMzJENjEwRTA7cGFyZW50Z3VpZD0</classCode><classificationItem><className>Administrative Boards</className><classCode>Z3VpZD11cm46dG9waWM6QTYwRUFCMDc5MzQ5NDEyREFEQkU2NkE2MjRGQTlCNzY7cGFyZW50Z3VpZD11cm46dG9waWM6Njg1MkM3RkYyNzIxNEVFRkJFMTI2NUM4NUU1ODdEM0Q</classCode></classificationItem><classificationItem><className>Assessments</className><classCode>Z3VpZD11cm46dG9waWM6MjA3MTI5NUFEQkY4NDkwREJGRjI1ODlDQjU5NzI4NkM7cGFyZW50Z3VpZD11cm46dG9waWM6MEY3NUIxODI2RjU2NEY0NzgwMDQyNjFDMEQ1QUExRjM</classCode></classificationItem><classificationItem><className>Boundaries</className><classCode>Z3VpZD11cm46dG9waWM6Qzg0MTI1ODBDMUY1NDUzN0JGRUQwMTYwQTlCMzAzRkE7cGFyZW50Z3VpZD11cm46dG9waWM6QURCRDNBRjBGRTE0NEFBRUEzNUU1MzFGQjg3MTM4MDI</classCode></classificationItem><classificationItem><className>Finance</className><classCode>Z3VpZD11cm46dG9waWM6MjMzOTBBRTg2MUVDNDdDNUE1M0QxNDk1RERCNjNCN0I7cGFyZW50Z3VpZD11cm46dG9waWM6Njg1MkM3RkYyNzIxNEVFRkJFMTI2NUM4NUU1ODdEM0Q</classCode></classificationItem><classificationItem><className>Financing</className><classCode>Z3VpZD11cm46dG9waWM6Q0QyN0IxRDI1MTE0NDQ3NkEzMzZCMTBCMkE2QkM3RTM7cGFyZW50Z3VpZD11cm46dG9waWM6MEY3NUIxODI2RjU2NEY0NzgwMDQyNjFDMEQ1QUExRjM</classCode></classificationItem></classificationItem><classificationItem><className>Tax Law</className><classCode>Z3VpZD11cm46dG9waWM6OTNEM0E2OEE0RkQyNEY1MDhBQzdGMkQ4ODI4QTJDODE7cGFyZW50Z3VpZD0</classCode><classificationItem><className>Assessments</className><classCode>Z3VpZD11cm46dG9waWM6MjIwOUNEOUU1RUQ5NEU3OTkyNUQxRjJFNkIzQjY3OTQ7cGFyZW50Z3VpZD11cm46dG9waWM6MjkxRkVDMkNDMjBGNDdFMkI1RDQ3Nzk4QjgwOTBGQjU</classCode></classificationItem><classificationItem><className>General Overview</className><classCode>Z3VpZD11cm46dG9waWM6MTdCMzZBOUNFNjAwNEZFM0E0NEU3ODJFM0EyRDMyNEI7cGFyZW50Z3VpZD11cm46dG9waWM6RUYwREVBQ0NGQ0UxNDY2REE0MzMzMDE5RDRGNTEyNjg</classCode></classificationItem><classificationItem><className>General Overview</className><classCode>Z3VpZD11cm46dG9waWM6QzQzNERBRTAxRDI0NDg4OUI1NzY1RjU4Q0IzRDVDODc7cGFyZW50Z3VpZD11cm46dG9waWM6MjkxRkVDMkNDMjBGNDdFMkI1RDQ3Nzk4QjgwOTBGQjU</classCode></classificationItem><classificationItem><className>General Overview</className><classCode>Z3VpZD11cm46dG9waWM6OUEzMjQ5ODcxNTZCNEE4QjkwQTI2M0QwRDU4RTRDRjU7cGFyZW50Z3VpZD11cm46dG9waWM6MjU1NzhGRDA0MUIyNERDOTlFRjU0M0I3RUE4QzE3MTg</classCode></classificationItem><classificationItem><className>General Overview</className><classCode>Z3VpZD11cm46dG9waWM6MEMzQzdEM0Q2NEEyNDg5RDhDMEE3NDAwMDNGOUU2MkM7cGFyZW50Z3VpZD11cm46dG9waWM6MEI0QjM4RDg1M0IxNDk1RDkwOTVGMEMxRTQxQTg1ODU</classCode></classificationItem><classificationItem><className>Imposition of Tax</className><classCode>Z3VpZD11cm46dG9waWM6QTA2MjBCODUyNEEzNDMxMjk4Qzc0RjEzM0ExMzQ3MTg7cGFyZW50Z3VpZD11cm46dG9waWM6MzRCRkI3RTBDNEE3NEQxQkE5Q0RGRTMxQTQyMkU4RDg</classCode></classificationItem><classificationItem><className>Imposition of Tax</className><classCode>Z3VpZD11cm46dG9waWM6Njg5MjQ4QzhCMzU5NDhCM0EzMTRCODg5OEQ2RkRFRkE7cGFyZW50Z3VpZD11cm46dG9waWM6MjU1NzhGRDA0MUIyNERDOTlFRjU0M0I3RUE4QzE3MTg</classCode></classificationItem></classificationItem><classificationItem><className>Transportation Law</className><classCode>Z3VpZD11cm46dG9waWM6RTYzRTk5RDVBQkQ2NDcwQzk2NTU3ODQ5OEE3NDlBNzk7cGFyZW50Z3VpZD0</classCode><classificationItem><className>Funding</className><classCode>Z3VpZD11cm46dG9waWM6QTFFNkIxMEVFQTA2NERDMDhDRUUwNUY2NEQ4MTYyOUM7cGFyZW50Z3VpZD11cm46dG9waWM6MjVCODE3RDNEMENDNDkxRjg5MzBBNTJFQkNCRDlFOEU</classCode></classificationItem><classificationItem><className>General Overview</className><classCode>Z3VpZD11cm46dG9waWM6NTkyRUE5REJENDMwNDE4OTg3OTg5NTg0OEVEOUE3M0E7cGFyZW50Z3VpZD11cm46dG9waWM6MjVCODE3RDNEMENDNDkxRjg5MzBBNTJFQkNCRDlFOEU</classCode></classificationItem><classificationItem><className>State &amp; Local Regulation</className><classCode>Z3VpZD11cm46dG9waWM6Qzg5MTM4OTVFMUUzNDQ5MEFBNEY3NTVGMEU0MTkzNzE7cGFyZW50Z3VpZD11cm46dG9waWM6MUJGMzIwOUU1NUY0NDU3MzhFRjhFRkMxQzgxOEI3MEY</classCode></classificationItem><classificationItem><className>Street Lights</className><classCode>Z3VpZD11cm46dG9waWM6RDI1NjBDODcwMTFFNENDREI2QzlBRjI0NTc1NkZFQ0I7cGFyZW50Z3VpZD11cm46dG9waWM6MjVCODE3RDNEMENDNDkxRjg5MzBBNTJFQkNCRDlFOEU</classCode></classificationItem><classificationItem><className>Waterways</className><classCode>Z3VpZD11cm46dG9waWM6NkYzREFDMEVBOUNGNDEwRjhFMzZFNzk0MzJCMjk2ODE7cGFyZW50Z3VpZD11cm46dG9waWM6MUJGMzIwOUU1NUY0NDU3MzhFRjhFRkMxQzgxOEI3MEY</classCode></classificationItem></classificationItem></classification><classificationGroup classificationScheme="indexing-terms"><classification classificationScheme="legal"><classificationItem><className>Business &amp; Corporate Compliance</className><classCode>Z3VpZD11cm46dG9waWM6MUFEMUQ2QTA1OUZCNEE5RjkzNTA2RERFMUNEOTk1RTI7cGFyZW50Z3VpZD0</classCode><classificationItem score="90"><className>Governments</className><classCode>Z3VpZD11cm46dG9waWM6MjdEQjE4OUJDMzQxNDNEMEI0RTI1QUFCMzJENjEwRTA7cGFyZW50Z3VpZD11cm46dG9waWM6MUFEMUQ2QTA1OUZCNEE5RjkzNTA2RERFMUNEOTk1RTI</classCode></classificationItem></classificationItem></classification></classificationGroup></metadata></legislativeDoc>